<?xml version="1.0" encoding="UTF-8"?>
<parliament:Propis xmlns:parliament="http://www.parliament.rs/schema"
 xmlns:security="http://www.w3.org/2000/09/xmldsig#"
 xmlns:xsi="http://www.w3.org/2001/XMLSchema-instance"
 xsi:schemaLocation="http://www.parliament.rs/schema file:/D:/GitHubRepos/xml_projekat/Parliament/Parliament.DataAccess/XmlSchema/Propis.xsd" parliament:DatumVremePredlaganja="2006-05-04T18:13:51.0" SerijskiBroj="50" parliament:Id="00000000-0000-0000-0000-000000000000">
    <parliament:Preambula>
        <parliament:NadlezniOrgan Uloga="Odbornik">
            <parliament:Ime>AA</parliament:Ime>
            <parliament:Prezime>AA</parliament:Prezime>
            <parliament:Email>0@0.0</parliament:Email>
        </parliament:NadlezniOrgan>
    </parliament:Preambula>
    <parliament:NazivPropisa>A</parliament:NazivPropisa>
    <parliament:Glava parliament:RedniBroj="50" parliament:Id="00000000-0000-0000-0000-000000000000">
        <parliament:NazivGlave>A</parliament:NazivGlave>
        <parliament:Odeljak parliament:RedniBroj="50" parliament:Id="00000000-0000-0000-0000-000000000000">
            <parliament:NazivOdeljka>1. </parliament:NazivOdeljka>
            <parliament:Clan parliament:RedniBroj="50" parliament:Id="00000000-0000-0000-0000-000000000000">
                <parliament:NazivClana>NazivClana0</parliament:NazivClana>
                <parliament:Stav parliament:RedniBroj="50" parliament:Id="00000000-0000-0000-0000-000000000000">
                    <parliament:TekstualniSadrzaj>TekstualniSadrzaj0</parliament:TekstualniSadrzaj>
                </parliament:Stav>
                <parliament:Stav parliament:RedniBroj="50" parliament:Id="00000000-0000-0000-0000-000000000000">
                    <parliament:Tacka parliament:RedniBroj="50" parliament:Id="00000000-0000-0000-0000-000000000000">
                        <parliament:Podtacka parliament:RedniBroj="50" parliament:Id="00000000-0000-0000-0000-000000000000">
                            <parliament:Alineja parliament:Id="00000000-0000-0000-0000-000000000000">Alineja0</parliament:Alineja>
                            <parliament:Alineja parliament:Id="00000000-0000-0000-0000-000000000000">Alineja1</parliament:Alineja>
                        </parliament:Podtacka>
                        <parliament:Podtacka parliament:RedniBroj="50" parliament:Id="00000000-0000-0000-0000-000000000000">
                            <parliament:Alineja parliament:Id="00000000-0000-0000-0000-000000000000">Alineja2</parliament:Alineja>
                            <parliament:Alineja parliament:Id="00000000-0000-0000-0000-000000000000">Alineja3</parliament:Alineja>
                        </parliament:Podtacka>
                    </parliament:Tacka>
                    <parliament:Tacka parliament:RedniBroj="50" parliament:Id="00000000-0000-0000-0000-000000000000">
                        <parliament:Podtacka parliament:RedniBroj="50" parliament:Id="00000000-0000-0000-0000-000000000000">
                            <parliament:TekstualniSadrzaj>TekstualniSadrzaj1</parliament:TekstualniSadrzaj>
                        </parliament:Podtacka>
                        <parliament:Podtacka parliament:RedniBroj="50" parliament:Id="00000000-0000-0000-0000-000000000000">
                            <parliament:Alineja parliament:Id="00000000-0000-0000-0000-000000000000">Alineja4</parliament:Alineja>
                            <parliament:Alineja parliament:Id="00000000-0000-0000-0000-000000000000">Alineja5</parliament:Alineja>
                        </parliament:Podtacka>
                    </parliament:Tacka>
                </parliament:Stav>
            </parliament:Clan>
            <parliament:Clan parliament:RedniBroj="50" parliament:Id="00000000-0000-0000-0000-000000000000">
                <parliament:NazivClana>NazivClana1</parliament:NazivClana>
                <parliament:Stav parliament:RedniBroj="50" parliament:Id="00000000-0000-0000-0000-000000000000">
                    <parliament:Tacka parliament:RedniBroj="50" parliament:Id="00000000-0000-0000-0000-000000000000">
                        <parliament:Podtacka parliament:RedniBroj="50" parliament:Id="00000000-0000-0000-0000-000000000000">
                            <parliament:Alineja parliament:Id="00000000-0000-0000-0000-000000000000">Alineja6</parliament:Alineja>
                            <parliament:Alineja parliament:Id="00000000-0000-0000-0000-000000000000">Alineja7</parliament:Alineja>
                        </parliament:Podtacka>
                        <parliament:Podtacka parliament:RedniBroj="50" parliament:Id="00000000-0000-0000-0000-000000000000">
                            <parliament:Alineja parliament:Id="00000000-0000-0000-0000-000000000000">Alineja8</parliament:Alineja>
                            <parliament:Alineja parliament:Id="00000000-0000-0000-0000-000000000000">Alineja9</parliament:Alineja>
                        </parliament:Podtacka>
                    </parliament:Tacka>
                    <parliament:Tacka parliament:RedniBroj="50" parliament:Id="00000000-0000-0000-0000-000000000000">
                        <parliament:TekstualniSadrzaj>TekstualniSadrzaj2</parliament:TekstualniSadrzaj>
                    </parliament:Tacka>
                </parliament:Stav>
                <parliament:Stav parliament:RedniBroj="50" parliament:Id="00000000-0000-0000-0000-000000000000">
                    <parliament:Tacka parliament:RedniBroj="50" parliament:Id="00000000-0000-0000-0000-000000000000">
                        <parliament:TekstualniSadrzaj>TekstualniSadrzaj3</parliament:TekstualniSadrzaj>
                    </parliament:Tacka>
                    <parliament:Tacka parliament:RedniBroj="50" parliament:Id="00000000-0000-0000-0000-000000000000">
                        <parliament:Podtacka parliament:RedniBroj="50" parliament:Id="00000000-0000-0000-0000-000000000000">
                            <parliament:Alineja parliament:Id="00000000-0000-0000-0000-000000000000">Alineja10</parliament:Alineja>
                            <parliament:Alineja parliament:Id="00000000-0000-0000-0000-000000000000">Alineja11</parliament:Alineja>
                        </parliament:Podtacka>
                        <parliament:Podtacka parliament:RedniBroj="50" parliament:Id="00000000-0000-0000-0000-000000000000">
                            <parliament:Alineja parliament:Id="00000000-0000-0000-0000-000000000000">Alineja12</parliament:Alineja>
                            <parliament:Alineja parliament:Id="00000000-0000-0000-0000-000000000000">Alineja13</parliament:Alineja>
                        </parliament:Podtacka>
                    </parliament:Tacka>
                </parliament:Stav>
            </parliament:Clan>
        </parliament:Odeljak>
        <parliament:Odeljak parliament:RedniBroj="50" parliament:Id="00000000-0000-0000-0000-000000000000">
            <parliament:NazivOdeljka>1. </parliament:NazivOdeljka>
            <parliament:Clan parliament:RedniBroj="50" parliament:Id="00000000-0000-0000-0000-000000000000">
                <parliament:NazivClana>NazivClana2</parliament:NazivClana>
                <parliament:TekstualniSadrzaj>TekstualniSadrzaj4</parliament:TekstualniSadrzaj>
            </parliament:Clan>
            <parliament:Clan parliament:RedniBroj="50" parliament:Id="00000000-0000-0000-0000-000000000000">
                <parliament:NazivClana>NazivClana3</parliament:NazivClana>
                <parliament:Stav parliament:RedniBroj="50" parliament:Id="00000000-0000-0000-0000-000000000000">
                    <parliament:Tacka parliament:RedniBroj="50" parliament:Id="00000000-0000-0000-0000-000000000000">
                        <parliament:Podtacka parliament:RedniBroj="50" parliament:Id="00000000-0000-0000-0000-000000000000">
                            <parliament:Alineja parliament:Id="00000000-0000-0000-0000-000000000000">Alineja14</parliament:Alineja>
                            <parliament:Alineja parliament:Id="00000000-0000-0000-0000-000000000000">Alineja15</parliament:Alineja>
                        </parliament:Podtacka>
                        <parliament:Podtacka parliament:RedniBroj="50" parliament:Id="00000000-0000-0000-0000-000000000000">
                            <parliament:TekstualniSadrzaj>TekstualniSadrzaj5</parliament:TekstualniSadrzaj>
                        </parliament:Podtacka>
                    </parliament:Tacka>
                    <parliament:Tacka parliament:RedniBroj="50" parliament:Id="00000000-0000-0000-0000-000000000000">
                        <parliament:TekstualniSadrzaj>TekstualniSadrzaj6</parliament:TekstualniSadrzaj>
                    </parliament:Tacka>
                </parliament:Stav>
                <parliament:Stav parliament:RedniBroj="50" parliament:Id="00000000-0000-0000-0000-000000000000">
                    <parliament:Tacka parliament:RedniBroj="50" parliament:Id="00000000-0000-0000-0000-000000000000">
                        <parliament:TekstualniSadrzaj>TekstualniSadrzaj7</parliament:TekstualniSadrzaj>
                    </parliament:Tacka>
                    <parliament:Tacka parliament:RedniBroj="50" parliament:Id="00000000-0000-0000-0000-000000000000">
                        <parliament:TekstualniSadrzaj>TekstualniSadrzaj8</parliament:TekstualniSadrzaj>
                    </parliament:Tacka>
                </parliament:Stav>
            </parliament:Clan>
        </parliament:Odeljak>
    </parliament:Glava>
    <parliament:Glava parliament:RedniBroj="50" parliament:Id="00000000-0000-0000-0000-000000000000">
        <parliament:NazivGlave>A</parliament:NazivGlave>
        <parliament:Odeljak parliament:RedniBroj="50" parliament:Id="00000000-0000-0000-0000-000000000000">
            <parliament:NazivOdeljka>1. </parliament:NazivOdeljka>
            <parliament:Pododeljak parliament:RedniBroj="50" parliament:Id="00000000-0000-0000-0000-000000000000">
                <parliament:NazivPododeljka>(a) </parliament:NazivPododeljka>
                <parliament:Clan parliament:RedniBroj="50" parliament:Id="00000000-0000-0000-0000-000000000000">
                    <parliament:NazivClana>NazivClana4</parliament:NazivClana>
                    <parliament:Stav parliament:RedniBroj="50" parliament:Id="00000000-0000-0000-0000-000000000000">
                        <parliament:Tacka parliament:RedniBroj="50" parliament:Id="00000000-0000-0000-0000-000000000000">
                            <parliament:TekstualniSadrzaj>TekstualniSadrzaj9</parliament:TekstualniSadrzaj>
                        </parliament:Tacka>
                        <parliament:Tacka parliament:RedniBroj="50" parliament:Id="00000000-0000-0000-0000-000000000000">
                            <parliament:Podtacka parliament:RedniBroj="50" parliament:Id="00000000-0000-0000-0000-000000000000">
                                <parliament:Alineja parliament:Id="00000000-0000-0000-0000-000000000000">Alineja16</parliament:Alineja>
                                <parliament:Alineja parliament:Id="00000000-0000-0000-0000-000000000000">Alineja17</parliament:Alineja>
                            </parliament:Podtacka>
                            <parliament:Podtacka parliament:RedniBroj="50" parliament:Id="00000000-0000-0000-0000-000000000000">
                                <parliament:Alineja parliament:Id="00000000-0000-0000-0000-000000000000">Alineja18</parliament:Alineja>
                                <parliament:Alineja parliament:Id="00000000-0000-0000-0000-000000000000">Alineja19</parliament:Alineja>
                            </parliament:Podtacka>
                        </parliament:Tacka>
                    </parliament:Stav>
                    <parliament:Stav parliament:RedniBroj="50" parliament:Id="00000000-0000-0000-0000-000000000000">
                        <parliament:Tacka parliament:RedniBroj="50" parliament:Id="00000000-0000-0000-0000-000000000000">
                            <parliament:TekstualniSadrzaj>TekstualniSadrzaj10</parliament:TekstualniSadrzaj>
                        </parliament:Tacka>
                        <parliament:Tacka parliament:RedniBroj="50" parliament:Id="00000000-0000-0000-0000-000000000000">
                            <parliament:TekstualniSadrzaj>TekstualniSadrzaj11</parliament:TekstualniSadrzaj>
                        </parliament:Tacka>
                    </parliament:Stav>
                </parliament:Clan>
                <parliament:Clan parliament:RedniBroj="50" parliament:Id="00000000-0000-0000-0000-000000000000">
                    <parliament:NazivClana>NazivClana5</parliament:NazivClana>
                    <parliament:Stav parliament:RedniBroj="50" parliament:Id="00000000-0000-0000-0000-000000000000">
                        <parliament:Tacka parliament:RedniBroj="50" parliament:Id="00000000-0000-0000-0000-000000000000">
                            <parliament:TekstualniSadrzaj>TekstualniSadrzaj12</parliament:TekstualniSadrzaj>
                        </parliament:Tacka>
                        <parliament:Tacka parliament:RedniBroj="50" parliament:Id="00000000-0000-0000-0000-000000000000">
                            <parliament:Podtacka parliament:RedniBroj="50" parliament:Id="00000000-0000-0000-0000-000000000000">
                                <parliament:TekstualniSadrzaj>TekstualniSadrzaj13</parliament:TekstualniSadrzaj>
                            </parliament:Podtacka>
                            <parliament:Podtacka parliament:RedniBroj="50" parliament:Id="00000000-0000-0000-0000-000000000000">
                                <parliament:TekstualniSadrzaj>TekstualniSadrzaj14</parliament:TekstualniSadrzaj>
                            </parliament:Podtacka>
                        </parliament:Tacka>
                    </parliament:Stav>
                    <parliament:Stav parliament:RedniBroj="50" parliament:Id="00000000-0000-0000-0000-000000000000">
                        <parliament:TekstualniSadrzaj>TekstualniSadrzaj15</parliament:TekstualniSadrzaj>
                    </parliament:Stav>
                </parliament:Clan>
            </parliament:Pododeljak>
            <parliament:Pododeljak parliament:RedniBroj="50" parliament:Id="00000000-0000-0000-0000-000000000000">
                <parliament:NazivPododeljka>(a) </parliament:NazivPododeljka>
                <parliament:Clan parliament:RedniBroj="50" parliament:Id="00000000-0000-0000-0000-000000000000">
                    <parliament:NazivClana>NazivClana6</parliament:NazivClana>
                    <parliament:Stav parliament:RedniBroj="50" parliament:Id="00000000-0000-0000-0000-000000000000">
                        <parliament:Tacka parliament:RedniBroj="50" parliament:Id="00000000-0000-0000-0000-000000000000">
                            <parliament:TekstualniSadrzaj>TekstualniSadrzaj16</parliament:TekstualniSadrzaj>
                        </parliament:Tacka>
                        <parliament:Tacka parliament:RedniBroj="50" parliament:Id="00000000-0000-0000-0000-000000000000">
                            <parliament:Podtacka parliament:RedniBroj="50" parliament:Id="00000000-0000-0000-0000-000000000000">
                                <parliament:TekstualniSadrzaj>TekstualniSadrzaj17</parliament:TekstualniSadrzaj>
                            </parliament:Podtacka>
                            <parliament:Podtacka parliament:RedniBroj="50" parliament:Id="00000000-0000-0000-0000-000000000000">
                                <parliament:Alineja parliament:Id="00000000-0000-0000-0000-000000000000">Alineja20</parliament:Alineja>
                                <parliament:Alineja parliament:Id="00000000-0000-0000-0000-000000000000">Alineja21</parliament:Alineja>
                            </parliament:Podtacka>
                        </parliament:Tacka>
                    </parliament:Stav>
                    <parliament:Stav parliament:RedniBroj="50" parliament:Id="00000000-0000-0000-0000-000000000000">
                        <parliament:TekstualniSadrzaj>TekstualniSadrzaj18</parliament:TekstualniSadrzaj>
                    </parliament:Stav>
                </parliament:Clan>
                <parliament:Clan parliament:RedniBroj="50" parliament:Id="00000000-0000-0000-0000-000000000000">
                    <parliament:NazivClana>NazivClana7</parliament:NazivClana>
                    <parliament:TekstualniSadrzaj>TekstualniSadrzaj19</parliament:TekstualniSadrzaj>
                </parliament:Clan>
            </parliament:Pododeljak>
        </parliament:Odeljak>
        <parliament:Odeljak parliament:RedniBroj="50" parliament:Id="00000000-0000-0000-0000-000000000000">
            <parliament:NazivOdeljka>1. </parliament:NazivOdeljka>
            <parliament:Pododeljak parliament:RedniBroj="50" parliament:Id="00000000-0000-0000-0000-000000000000">
                <parliament:NazivPododeljka>(a) </parliament:NazivPododeljka>
                <parliament:Clan parliament:RedniBroj="50" parliament:Id="00000000-0000-0000-0000-000000000000">
                    <parliament:NazivClana>NazivClana8</parliament:NazivClana>
                    <parliament:TekstualniSadrzaj>TekstualniSadrzaj20</parliament:TekstualniSadrzaj>
                </parliament:Clan>
                <parliament:Clan parliament:RedniBroj="50" parliament:Id="00000000-0000-0000-0000-000000000000">
                    <parliament:NazivClana>NazivClana9</parliament:NazivClana>
                    <parliament:TekstualniSadrzaj>TekstualniSadrzaj21</parliament:TekstualniSadrzaj>
                </parliament:Clan>
            </parliament:Pododeljak>
            <parliament:Pododeljak parliament:RedniBroj="50" parliament:Id="00000000-0000-0000-0000-000000000000">
                <parliament:NazivPododeljka>(a) </parliament:NazivPododeljka>
                <parliament:Clan parliament:RedniBroj="50" parliament:Id="00000000-0000-0000-0000-000000000000">
                    <parliament:NazivClana>NazivClana10</parliament:NazivClana>
                    <parliament:TekstualniSadrzaj>TekstualniSadrzaj22</parliament:TekstualniSadrzaj>
                </parliament:Clan>
                <parliament:Clan parliament:RedniBroj="50" parliament:Id="00000000-0000-0000-0000-000000000000">
                    <parliament:NazivClana>NazivClana11</parliament:NazivClana>
                    <parliament:TekstualniSadrzaj>TekstualniSadrzaj23</parliament:TekstualniSadrzaj>
                </parliament:Clan>
            </parliament:Pododeljak>
        </parliament:Odeljak>
    </parliament:Glava>
    <security:Signature>
        <security:SignedInfo>
            <security:CanonicalizationMethod Algorithm="http://www.oxygenxml.com/">
            </security:CanonicalizationMethod>
            <security:SignatureMethod Algorithm="http://www.oxygenxml.com/">
            </security:SignatureMethod>
            <security:Reference>
                <security:DigestMethod Algorithm="http://www.oxygenxml.com/">
                </security:DigestMethod>
                <security:DigestValue>ZGVmYXVsdA==</security:DigestValue>
            </security:Reference>
            <security:Reference>
                <security:DigestMethod Algorithm="http://www.oxygenxml.com/">
                </security:DigestMethod>
                <security:DigestValue>ZGVmYXVsdA==</security:DigestValue>
            </security:Reference>
        </security:SignedInfo>
        <security:SignatureValue>ZGVmYXVsdA==</security:SignatureValue>
    </security:Signature>
</parliament:Propis>
